uv_publish/__init__.py
uv_publish/cli.py
uv_publish/lib.py
uv_publish/logging.py
uv_publish/settings.py
dycw_uv_publish-0.5.6.dist-info/WHEEL
dycw_uv_publish-0.5.6.dist-info/entry_points.txt
dycw_uv_publish-0.5.6.dist-info/METADATA
dycw_uv_publish-0.5.6.dist-info/RECORD
